setup.py
asciigif/__init__.py
asciigif.egg-info/PKG-INFO
asciigif.egg-info/SOURCES.txt
asciigif.egg-info/dependency_links.txt
asciigif.egg-info/not-zip-safe
asciigif.egg-info/top_level.txt