Metadata-Version: 1.0
Name: asciigif
Version: 0.1
Summary: Text-based GIF generation / output
Home-page: https://github.com/CakeGamingHub/AsciiGIF
Author: Motherflippin
Author-email: cakephone5@gmail.com
License: MIT
Platform: UNKNOWN
